{"Title":"Bohr atom","Slides":[{"startTime":"","endTime":"","startMarkerName":"","endMarkerName":"","headlines":[],"bullets":[]},{"startTime":"","endTime":"","startMarkerName":"","endMarkerName":"","headlines":["Change in energy alters orbital size"],"bullets":[]},{"startTime":"","endTime":"","startMarkerName":"","endMarkerName":"","headlines":["Change in energy alters orbital size"],"bullets":[]},{"startTime":"","endTime":"","startMarkerName":"","endMarkerName":"","headlines":["Orbits are quantized"],"bullets":[]}]}