{"Title":"Calculating center of mass","Slides":[{"startTime":"0","endTime":"12900","startMarkerName":"Introduction","endMarkerName":"Marker 2","headlines":["  <span class=\"math\">    <i>x</i>    <sub>CM</sub> = <i>x</i> position of center of mass,</span>  <span class=\"math\">    <i>m</i>    <sub>1</sub> = mass of object 1,</span>  <span class=\"math\">    <i>x</i>    <sub>1</sub> = <i>x</i> position of object 1,</span>  <span class=\"math\">    <i>m</i>    <sub>2</sub> = mass of object 2,</span>  <span class=\"math\">    <i>x</i>    <sub>2</sub> = <i>x</i> position of object 2</span>"],"bullets":[]},{"startTime":"13900","endTime":"-1","startMarkerName":"Marker 1","endMarkerName":"End","headlines":["  <span class=\"math\">    <i>x</i>    <sub>CM</sub> = <i>x</i> position of center of mass,</span>  <span class=\"math\">    <i>m</i>    <sub>1</sub> = mass of object 1,</span>  <span class=\"math\">    <i>x</i>    <sub>1</sub> = <i>x</i> position of object 1,</span>  <span class=\"math\">    <i>m</i>    <sub>2</sub> = mass of object 2,</span>  <span class=\"math\">    <i>x</i>    <sub>2</sub> = <i>x</i> position of object 2</span>"],"bullets":[]}]}