{"Title":"Communicating, applying scientific information ","Slides":[{"startTime":"","endTime":"","startMarkerName":"","endMarkerName":"","headlines":[],"bullets":[]},{"startTime":"","endTime":"","startMarkerName":"","endMarkerName":"","headlines":["Discuss"],"bullets":[]},{"startTime":"","endTime":"","startMarkerName":"","endMarkerName":"","headlines":["State the data you use "],"bullets":[]},{"startTime":"","endTime":"","startMarkerName":"","endMarkerName":"","headlines":["List sources of uncertainty"],"bullets":[]}]}