{"Title":"Elastic collision","Slides":[{"startTime":"0","endTime":"17800","startMarkerName":"Introduction","endMarkerName":"Marker 3","headlines":[],"bullets":[]},{"startTime":"18800","endTime":"27300","startMarkerName":"Marker 2","endMarkerName":"Marker 5","headlines":["Kinetic energy is conserved"],"bullets":[]},{"startTime":"28300","endTime":"-1","startMarkerName":"Marker 4","endMarkerName":"End","headlines":["Kinetic energy is conserved"],"bullets":["Total <i>KE</i> of system remains constant"]}]}