{"Title":"Vertical projectile motion properties","Slides":[{"startTime":"0","endTime":"41767","startMarkerName":"Introduction","endMarkerName":"Marker 2","headlines":["Projectile accelerates at −<i>g</i>"],"bullets":[]},{"startTime":"42767","endTime":"53000","startMarkerName":"Marker 1","endMarkerName":"Marker 2","headlines":["Projectile accelerates at −<i>g</i>"],"bullets":["Horizontal line "]},{"startTime":"54000","endTime":"84033","startMarkerName":"Marker 3","endMarkerName":"Marker 6","headlines":["Velocity in freefall"],"bullets":["Line with negative slope"]},{"startTime":"85033","endTime":"97700","startMarkerName":"Marker 4","endMarkerName":"Marker 7","headlines":["Velocity in freefall"],"bullets":["Line with negative slope"]},{"startTime":"98700","endTime":"-1","startMarkerName":"Marker 5","endMarkerName":"End","headlines":["Vertical position"],"bullets":["A parabola"]}]}