{"Title":"Photon","Slides":[{"startTime":"0","endTime":"14800","startMarkerName":"Introduction","endMarkerName":"Marker 1","headlines":["Packet of energy"],"bullets":[]},{"startTime":"15833","endTime":"28033","startMarkerName":"Marker 2","endMarkerName":"Marker 3","headlines":["Packet of energy"],"bullets":["Light is quantized"]},{"startTime":"29033","endTime":"-1","startMarkerName":"Marker 4","endMarkerName":"End","headlines":["Packet of energy"],"bullets":["Light is quantized","Brighter light = more photons"]}]}