{"Title":"Strong force","Slides":[{"startTime":"0","endTime":"6667","startMarkerName":"Introduction","endMarkerName":"Marker 2","headlines":[],"bullets":[]},{"startTime":"7667","endTime":"28733","startMarkerName":"Marker 1","endMarkerName":"Marker 4","headlines":["Holds particles in nucleus together"],"bullets":[]},{"startTime":"29733","endTime":"41233","startMarkerName":"Marker 3","endMarkerName":"Marker 5","headlines":["Is very strong!"],"bullets":[]},{"startTime":"42233","endTime":"61267","startMarkerName":"Marker 6","endMarkerName":"Marker 8","headlines":["Always attractive, regardless of charge"],"bullets":[]},{"startTime":"62267","endTime":"73633","startMarkerName":"Marker 7","endMarkerName":"Marker 9","headlines":["Always attractive, regardless of charge"],"bullets":[]},{"startTime":"74633","endTime":"-1","startMarkerName":"Marker 10","endMarkerName":"End","headlines":["Acts only over a very short range"],"bullets":[]}]}