{"Title":"Second law of thermodynamics","Slides":[{"startTime":"0","endTime":"6200","startMarkerName":"Introduction","endMarkerName":"Marker 2","headlines":[],"bullets":[]},{"startTime":"7200","endTime":"15400","startMarkerName":"Marker 1","endMarkerName":"Marker 3","headlines":["Engines cannot convert 100% of heat into work during a cycle"],"bullets":[]},{"startTime":"16400","endTime":"27500","startMarkerName":"Marker 2","endMarkerName":"Marker 4","headlines":["Engines cannot convert 100% of heat into work during a cycle"],"bullets":[]},{"startTime":"28500","endTime":"-1","startMarkerName":"Marker 3","endMarkerName":"End","headlines":["Engines cannot convert 100% of heat into work during a cycle"],"bullets":[]}]}