{"cards":[{"lines":[{"type":"title","text":"Temperature"},{"type":"headline","text":"Describes average translational kinetic energy"},{"type":"headline","text":"Is measured by thermometers"}]}],"definitions":[{"term":"Temperature","def":"Measured by thermometers, it describes the average kinetic energy of molecules in matter."}],"secText":["Temperature is a measure of the kinetic component of thermal energy.  ","Temperature describes the average translational kinetic energy of the molecules that make up matter. When they move faster, temperature increases.  ","Thermometers measure temperature.  This is a very simple sentence \u2212 and sometimes it is used as the definition of temperature. "],"objNames":["wb_thermal_energy_temperature1"]}