{
  "cards": [
    {
      "lines": [
        {
          "type": "title",
          "text": "Gravitational force"
        },
        {
          "type": "headline",
          "text": "Objects apply equal amounts of force on each other"
        },
        {
          "type": "headline",
          "text": "Proportional to masses of bodies"
        },
        {
          "type": "headline",
          "text": "Inversely proportional to square of distance"
        }
      ]
    },
    {
      "lines": [
        {
          "type": "title",
          "text": "Value for <i>g</i> varies"
        },
        {
          "type": "headline",
          "text": "Because of altitude"
        }
      ]
    }
  ],
  "definitions": [],
  "secText": [
    "  <b>Essential Question: </b>  <b>    <br />  </b>How can we calculate the gravitational force between two objects?",
    "  <b>Enduring Understandings:</b>  <b>    <br />  </b>1. The <a class='pjumpToTopic' href='javascript:void(0)' data-chap='8' data-topic='2' data-subtopic='1' data-subsection='1'>gravitational force</a> between two objects can be calculated by multiplying the gravitational constant by the mass of object one and the mass of object two, divided by the distance squared between the two objects.<br />2. <a class='pjumpToTopic' href='javascript:void(0)' data-chap='8' data-topic='2' data-subtopic='2' data-subsection='0'>G</a>, the gravitational constant, is constant everywhere in the universe. <a class='pjumpToTopic' href='javascript:void(0)' data-chap='8' data-topic='2' data-subtopic='2' data-subsection='0'>g</a> varies by planet.<br />3. Earth's shape and composition explain why <a class='pjumpToTopic' href='javascript:void(0)' data-chap='8' data-topic='2' data-subtopic='2' data-subsection='0'>g can vary</a> on the same planet.",
    "  <b>Vocabulary:</b>  <a class='pjumpToTopic' href='javascript:void(0)' data-chap='8' data-topic='2' data-subtopic='1' data-subsection='1'>gravity</a>, <a class='pjumpToTopic' href='javascript:void(0)' data-chap='8' data-topic='2' data-subtopic='1' data-subsection='1'>Newton's law of gravity</a>",
    "  <b>STEM Skills:</b>  <b>    <br />  </b>1. Review <a class='pjumpToTopic' href='javascript:void(0)' data-chap='2' data-topic='3' data-subtopic='1' data-subsection='0'>freefall acceleration</a>."
  ],
  "objNames": [
    "wb_newton_equation_concept",
    "wb_g_on_Earth1"
  ]
}