{"cards":[{"lines":[{"type":"title","text":"Heisenberg uncertainty principle"},{"type":"headline","text":"Theoretical limitation of measurement precision"},{"type":"headline","text":"Both position and momentum <u>cannot<\/u> be precisely measured simultaneously "}]},{"lines":[{"type":"title","text":"Calculating a matter particle\u2019s wavelength"},{"type":"headline","text":"Matter wavelengths are very small"},{"type":"bullet","text":"Planck\u2019s constant = 6.63 \u00d7 10<sup class=\"\">\u221234<\/sup> J<span class=\"Symbols\">\u00b7<\/span>s "}]}],"definitions":[],"secText":["  <b>Lesson:<\/b>  <b>    <br \/>  <\/b>1. Describe <a class='pjumpToTopic' href='javascript:void(0)' data-chap='23' data-topic='3' data-subtopic='1' data-subsection='0'>matter waves<\/a>.<br \/>2. <a class='pjumpToTopic' href='javascript:void(0)' data-chap='23' data-topic='3' data-subtopic='2' data-subsection='0'>Compare and contrast<\/a> light interference patterns to electron interference patterns.<br \/>3. Apply the concept of matter waves to a <a class='pjumpToTopic' href='javascript:void(0)' data-chap='23' data-topic='3' data-subtopic='2' data-subsection='1'>transmission electron microscope<\/a>.<br \/>4. Define the <a class='pjumpToTopic' href='javascript:void(0)' data-chap='23' data-topic='3' data-subtopic='3' data-subsection='0'>Heisenberg uncertainty principle<\/a>.<br \/>5. Determine the <a class='pjumpToTopic' href='javascript:void(0)' data-chap='23' data-topic='3' data-subtopic='3' data-subsection='1'>probability<\/a> of the location of an electron in an atom.<br \/>6. <a class='pjumpToTopic' href='javascript:void(0)' data-chap='23' data-topic='3' data-subtopic='4' data-subsection='0'>Describe<\/a> Schr\u00f6dinger's thought experiment.<br \/>7. <a class='pjumpToTopic' href='javascript:void(0)' data-chap='23' data-topic='3' data-subtopic='4' data-subsection='1'>Describe<\/a> the results of Schr\u00f6dinger's thought experiment.<br \/>8. Calculate the <a class='pjumpToTopic' href='javascript:void(0)' data-chap='23' data-topic='3' data-subtopic='5' data-subsection='0'>wavelength of matter<\/a>.","  <b>Homework:<\/b>  <span class=\"KBInternalLink\"><a href=\"assign.html#OHW 23.04\">OHW 23.04<\/a><\/span>","  <b>Quick Review:<\/b>  <a class='pjumpToVideo' href='javascript:void(0)' data-video='true' data-vref='sum_matter_waves'>Matter Waves<\/a>"],"objNames":["wb_heisenberg","wb_matter_waves_equation"]}