{
  "cards": [
    {
      "lines": [
        {
          "type": "title",
          "text": "Adding vectors using components"
        },
        {
          "type": "headline",
          "text": "Identify components"
        },
        {
          "type": "bullet",
          "text": "A = (2, 1), <span class=\"math\">B = (3, −2)</span>"
        },
        {
          "type": "headline",
          "text": "A + B = (<i>A</i><sub class=\"\">x</sub> + <i>B</i><sub class=\"\">x</sub>, <i>A</i><sub class=\"\">y</sub> + <i>B</i><sub class=\"\">y</sub>)"
        },
        {
          "type": "bullet",
          "text": "  <span class=\"math\">A + B = (2 + 3, 1 + (−2)) = (5, −1)</span>"
        }
      ]
    }
  ],
  "definitions": [],
  "secText": [
   "  <b>Essential Question: </b>  <br />How can we combine two vectors?",
    "  <b>Enduring Understandings:</b>  <b>    <br />  </b>1. <a class='pjumpToTopic' href='javascript:void(0)' data-chap='4' data-topic='3' data-subtopic='1'>Vectors can be combined</a> by adding or subtracting the components of each vector.",
    "  <b>Vocabulary:</b>  <a class='pjumpToTopic' href='javascript:void(0)' data-chap='4' data-topic='3' data-subtopic='1'>adding vectors using components</a>",
    "  <b>STEM Skills:</b>  <b>    <br />  </b>1. Review <a class='pjumpToTopic' href='javascript:void(0)' data-chap='4' data-topic='0' data-subtopic='2'>vector components</a>."
  ],
  "objNames": [
    "wb_math_add_vectors_components_concept"
  ]
}