{"cards":[{"lines":[{"type":"title","text":"Inversely proportional"},{"type":"headline","text":"Relationship that can be described as <math><mrow><mi>y<\/mi><mo>=<\/mo><mfrac linethickness=\"thin\"><mi>k<\/mi><mi>x<\/mi><\/mfrac><\/mrow><\/math>"},{"type":"headline","text":"Graph is a curve"}]},{"lines":[{"type":"title","text":"Slope equals rate"},{"type":"headline","text":"  <math>    <mrow>      <mtext>Slope\u00a0=\u00a0<\/mtext>      <mfrac linethickness=\"thin\">        <mrow>          <mtext>30\u00a0gallons\u00a0<\/mtext>          <mo>\u2212<\/mo>          <mtext>\u00a010\u00a0gallons<\/mtext>        <\/mrow>        <mrow>          <mtext>15\u00a0seconds\u00a0<\/mtext>          <mo>\u2212<\/mo>          <mtext>\u00a05\u00a0seconds<\/mtext>        <\/mrow>      <\/mfrac>      <mo>=<\/mo>      <mfrac linethickness=\"thin\">        <mrow>          <mtext>2\u00a0gallons<\/mtext>        <\/mrow>        <mrow>          <mtext>1\u00a0second<\/mtext>        <\/mrow>      <\/mfrac>    <\/mrow>  <\/math>"}]}],"definitions":[],"secText":["  <b>Essential Question: <\/b>  <b>    <br \/>  <\/b>How can we analyze equations using data and graphs?","  <b>Enduring Understandings:<\/b>  <b>    <br \/>  <\/b>1. Classify relationships as <a class='pjumpToTopic' href='javascript:void(0)' data-chap='2' data-topic='0' data-subtopic='1' data-subsection='0'>proportional and linear<\/a>, <a class='pjumpToTopic' href='javascript:void(0)' data-chap='2' data-topic='0' data-subtopic='1' data-subsection='1'>inversely proportional, and nonlinear<\/a>.<b><br \/><\/b>2. Identify and calculate <a class='pjumpToTopic' href='javascript:void(0)' data-chap='2' data-topic='0' data-subtopic='2' data-subsection='0'>rates<\/a> in graphs.","  <b>Vocabulary:<\/b>  <a class='pjumpToTopic' href='javascript:void(0)' data-chap='2' data-topic='0' data-subtopic='1' data-subsection='0'>proportional relationship<\/a>, <a class='pjumpToTopic' href='javascript:void(0)' data-chap='2' data-topic='0' data-subtopic='1' data-subsection='0'>linear relationship<\/a>, <a class='pjumpToTopic' href='javascript:void(0)' data-chap='2' data-topic='0' data-subtopic='1' data-subsection='1'>inversely proportional<\/a>, <a class='pjumpToTopic' href='javascript:void(0)' data-chap='2' data-topic='0' data-subtopic='1' data-subsection='1'>nonlinear<\/a>, <a class='pjumpToTopic' href='javascript:void(0)' data-chap='2' data-topic='0' data-subtopic='2' data-subsection='0'>rate<\/a>","  <b>STEM Skills:<\/b>  <b>    <br \/>  <\/b>1. <a class='pjumpToVideo' href='javascript:void(0)' data-video='true' data-vref='wb_math_rate_aquarium3'>Analyze graphs<\/a>.<b><br \/><\/b>2. <a class='pjumpToTopic' href='javascript:void(0)' data-chap='2' data-topic='0' data-subtopic='2' data-subsection='0'>Calculate slope<\/a>."],"objNames":["wb_math_inversely_proportional","wb_math_rate_aquarium2"]}