{
  "cards": [
    {
      "lines": [
        {
          "type": "title",
          "text": "Kinetic energy"
        },
        {
          "type": "headline",
          "text": "Energy of motion"
        },
        {
          "type": "headline",
          "text": "Proportional to"
        },
        {
          "type": "bullet",
          "text": "mass"
        },
        {
          "type": "bullet",
          "text": "square of speed"
        }
      ]
    },
    {
      "lines": [
        {
          "type": "title",
          "text": "Work"
        },
        {
          "type": "headline",
          "text": "Changes an object’s energy"
        },
        {
          "type": "bullet",
          "text": "Work can increase an object’s energy"
        },
        {
          "type": "bullet",
          "text": "Work can reduce an object’s energy"
        }
      ]
    }
  ],
  "definitions": [],
  "secText": [
    "  <b>Essential Question: </b>  <b>    <br />  </b>How does kinetic energy relate to work?",
    "  <b>Enduring Understandings:</b>  <b>    <br />  </b>1. There are many different forms of <a class='pjumpToTopic' href='javascript:void(0)' data-chap='6' data-topic='2' data-subtopic='1' data-subsection='0'>energy</a>, such as chemical, kinetic, potential, and electric. Work changes the amount of energy of an object.<br />2. <a class='pjumpToTopic' href='javascript:void(0)' data-chap='6' data-topic='2' data-subtopic='2' data-subsection='0'>Kinetic energy</a> is the energy of motion of an object. The kinetic energy of an object can be calculated by multiplying an object's mass by its velocity squared divided by 2.<br />3. The <a class='pjumpToTopic' href='javascript:void(0)' data-chap='6' data-topic='2' data-subtopic='3' data-subsection='0'>net amount of work</a> is equal to the change in kinetic energy of an object.  ",
    "  <b>Vocabulary:</b>  <a class='pjumpToTopic' href='javascript:void(0)' data-chap='6' data-topic='2' data-subtopic='1' data-subsection='0'>energy</a>, <a class='pjumpToTopic' href='javascript:void(0)' data-chap='6' data-topic='2' data-subtopic='2' data-subsection='0'>kinetic energy</a>",
    "  <b>STEM Skills:</b>  <b>    <br />  </b>1. <a class='pjumpToTopic' href='javascript:void(0)' data-chap='1' data-topic='0' data-subtopic='5' data-subsection='0'>Solve an equation</a> for a variable."
  ],
  "objNames": [
    "wb_kinetic_energy_definition",
    "wb_work_energy_concept"
  ]
}